{
  "name": "Researcher",
  "fields": [
    {
      "fieldName": "firstName",
      "fieldType": "String"
    },
    {
      "fieldName": "lastName",
      "fieldType": "String"
    },
    {
      "fieldName": "middleName",
      "fieldType": "String"
    },
    {
      "fieldName": "birthDate",
      "fieldType": "LocalDate"
    }
  ],
  "relationships": [
    {
      "relationshipType": "one-to-one",
      "otherEntityName": "portalUser",
      "otherEntityRelationshipName": "researcher",
      "relationshipName": "portalUser",
      "ownerSide": false
    },
    {
      "relationshipType": "many-to-many",
      "otherEntityName": "researchInstitution",
      "otherEntityRelationshipName": "researchers",
      "relationshipName": "institutions",
      "otherEntityField": "id",
      "ownerSide": false
    }
  ],
  "changelogDate": "20230622064129",
  "entityTableName": "researcher",
  "dto": "no",
  "pagination": "no",
  "service": "no",
  "jpaMetamodelFiltering": false,
  "fluentMethods": true,
  "readOnly": false,
  "embedded": false,
  "clientRootFolder": "",
  "applications": "*"
}
